design.sv
// Code your design here
`timescale 1ns / 1ps
//////////////////////////////////////////////////////////////////////////////////
// Company: 
// Engineer: 
// 
// Create Date:    19:23:43 05/03/2024 
// Design Name: 
// Module Name:    TinyMIPS 
// Project Name: 
// Target Devices: 
// Tool versions: 
// Description: 
//
// Dependencies: 
//
// Revision: 
// Revision 0.01 - File Created
// Additional Comments: 
//
//////////////////////////////////////////////////////////////////////////////////
module TinyMIPS(clk, rst, data_fromRAM, wrEn, addr_toRAM, data_toRAM);
	input clk, rst;
	output reg wrEn;
	input [15:0] data_fromRAM;
	output reg [15:0] data_toRAM;
	output reg [7:0] addr_toRAM;

	reg [2:0] st, stN;
	reg [7:0] PC, PCN;
	reg [15:0] IW, IWN;
	reg [15:0] T1, T1N, T2, T2N;

	reg [15:0] RF [7:0];

	always @(posedge clk) begin
		st <= stN;
		PC <= PCN;
		IW <= IWN;
		T1 <= T1N;
		T2 <= T2N;
	end

	always @ * begin
		if (rst) begin
			stN = 3'd0;
			PCN = 8'd0;
		end
		else begin
			wrEn = 1'b0;
			PCN = PC;
			IWN = IW;
			stN = 3'dx;
			addr_toRAM = 8'hX;
			data_toRAM = 16'hX;
			T1N = 16'hX;
			T2N = 16'hX;
			
			case (st)
				3'd0: begin // S0: Fetch State
					addr_toRAM = PC;
					stN = 3'd1;
				end
				3'd1: begin // S1 State
					IWN = data_fromRAM;
					if(data_fromRAM[15:12] == 4'b0000) begin // ADD
						T1N = RF[data_fromRAM[8:6]];
						stN = 3'd2;
					end
					else if(data_fromRAM[15:12] == 4'b0001) begin // ADDi
						T1N = RF[data_fromRAM[8:6]];
						stN = 3'd2;
					end
					else if(data_fromRAM[15:12] == 4'b0111) begin // CPi
						RF[data_fromRAM[11:9]] = {7'd0,data_fromRAM[8:0]};
						PCN = PC + 8'd1;
						stN = 3'd0;
					end
					else if(data_fromRAM[15:12] == 4'b1001) begin // BLT
						T1N = RF[data_fromRAM[11:9]];
						stN = 3'd2;
					end
                  	else if(data_fromRAM[15:12] == 4'b0010) begin // MUL 
                  		T1N = RF[data_fromRAM[8:6]];
                    	stN = 3'd2;
                  	end
                  	else if(data_fromRAM[15:12] == 4'b0011)begin // SRL
                    	T1N = RF[data_fromRAM[8:6]];
                    	stN = 3'd2;
                 	 end
                  	else if ( data_fromRAM[15:12] == 4'b0100)begin // LD
						T1N = RF[data_fromRAM[8:6]];
						stN = 3'd2;
                  	end
                  	else if (data_fromRAM[15:12] == 4'b0101) begin // ST
						T1N = RF[data_fromRAM[8:6]];
						stN = 3'd2;
                  	end
                    else if (data_fromRAM[15:12] == 4'b0110) begin // CP
                    	T1N = RF[data_fromRAM[8:6]];
						stN = 3'd2;
                  	end
                    else if (data_fromRAM[15:12] == 4'b1000) begin // BEQ
                        T1N = RF[data_fromRAM[11:9]];
                      	stN = 3'd2;
                  	end
                   else if (data_fromRAM[15:12] == 4'b1010) begin // BGT
                        T1N = RF[data_fromRAM[11:9]];
                     	stN = 3'd2;
                  	end   	
				end
				3'd2: begin // S2 State
					if (IW[15:12]==4'b0000) begin // ADD
						T1N = T1;
						T2N = RF[IW[5:3]];
						stN = 3'd3;
					end
					else if (IW[15:12]==4'b0001) begin // ADDi
						RF[IW[11:9]] = T1 + {{2{IW[5]}}, IW[5:0]};
						PCN = PC + 8'd1;
						stN = 3'd0;
					end
					else if(IW[15:12] == 4'b1001) begin // BLT
						T2N = RF[IW[8:6]];
						T1N = T1;
						stN = 3'd3;
					end
                  	else if (IW[15:12] == 4'b0010) begin // MUL
                      	T1N = T1;
                      	T2N = RF[IW[5:3]];
						stN = 3'd3;
                    end
                  	else if (IW[15:12] == 4'b0011) begin // SRL
                      	T2N = RF[IW[5:3]];
                      	T1N = T1;
                      	stN =3'd3;
                    end
                  	else if (IW[15:12] == 4'b0100) begin // LD
                      	T2N = T1 + IW[5:0];
                      	T1N = T1;
                      	stN = 3'd3;
                      
                    end
                  	else if (IW[15:12] == 4'b0101)begin // ST
                      	T2N = T1 + IW[5:0];
                      	T1N = T1;
                      	stN = 3'd3;
                    end
                  	else if (IW[15:12]  == 4'b0110 )begin // CP
                        RF[IW[11:9]]  = T1;
                        PCN = PC + 8'd1;
                      	stN = 3'd0;
                  	end
                  	else if (IW[15:12]  == 4'b1000)begin // BEQ
                      	T2N = RF[IW[8:6]];
                      	T1N = T1;
                      	stN = 3'd3;
                    end
                  	else if (IW[15:12] == 4'b1010)begin //BGT
                      	T2N = RF[IW[8:6]];
                      	T1N = T1;
                      	stN = 3'd3;
                    end
                end
				3'd3: begin // S3 State
					if (IW[15:12]==4'b0000) begin // ADD
						RF[IW[11:9]] = T1 + T2;
						PCN = PC + 8'd1;
						stN = 3'd0;
					end
					else if (IW[15:12]==4'b1001) begin // BLT
						PCN = (T1 < T2) ? (PC + {{2{IW[5]}}, IW[5:0]}) : (PC + 8'd1);// PC+signext(imm) or PC+1
						stN = 3'd0;
					end
                  	else if(IW[15:12] == 4'b0010) begin //MUL
                      RF[IW[11:9]] = T1 * T2;
                      PCN = PC + 8'd1;
                      stN = 3'd0;
                    end
                  	else if(IW[15:12] == 4'b0011) begin	// SRL
                      RF[IW[11:9]] = ( T2 < 32 ) ? (T1 >> T2) : (T1 << (T2-32));
					  PCN = PC + 8'd1;
                      stN = 3'd0;
                    end
                 	else if(IW[15:12] == 4'b0100) begin	// LD
                      RF[IW[11:9]] = data_fromRAM[T2];
                      PCN = PC + 8'd1;
					  addr_toRAM = T2;
                      stN = 3'd0;
                    end
                  	else if(IW[15:12] == 4'b0101) begin	// ST
                      data_toRAM[T2] = RF[IW[11:9]];
                      PCN = PC + 8'd1;
                      addr_toRAM = T2;
                      stN = 3'd0;
                    end
                  	else if(IW[15:12] == 4'b1000) begin	// BEQ
                      PCN = (T1 == T2) ? (PC + {{2{IW[5]}}, IW[5:0]}): (PC + 8'd1);
                      stN = 3'd0;
                    end
                  	else if(IW[15:12] == 4'b1010) begin	// BGT
                      PCN = (T1 > T2) ? (PC + {{2{IW[5]}}, IW[5:0]}): (PC + 8'd1);
                      stN = 3'd0;
                    end
    			end
			endcase
		end // else
	end // always
endmodule

module blram(clk, rst, we, addr, din, dout);
	parameter SIZE = 8, DEPTH = 2**SIZE;
	input clk;
	input rst;
	input we;
	input [SIZE-1:0] addr;
	input [15:0] din;
	output reg [15:0] dout;
	
	reg [15:0] mem [DEPTH-1:0];
 
	always @(posedge clk) begin
		dout <= mem[addr[SIZE-1:0]];
		if (we)
			mem[addr[SIZE-1:0]] <= din;
	end
endmodule

testbench.sv
// Code your testbench here
// or browse Examples
`timescale 1ns / 1ps

////////////////////////////////////////////////////////////////////////////////
// Company: 
// Engineer:
//
// Create Date:   19:49:42 05/03/2024
// Design Name:   TinyMIPS
// Module Name:   C:/Users/gurhan/Desktop/gurhan/CSE224/sp24/Project/TinyMIPS/tb_TinyMIPS.v
// Project Name:  TinyMIPS
// Target Device:  
// Tool versions:  
// Description: 
//
// Verilog Test Fixture created by ISE for module: TinyMIPS
//
// Dependencies:
// 
// Revision:
// Revision 0.01 - File Created
// Additional Comments:
// 
////////////////////////////////////////////////////////////////////////////////

module tb_TinyMIPS;
	parameter SIZE = 8, DEPTH = 2**SIZE;
	reg clk, rst;
	wire wrEn;
	wire [SIZE-1:0] addr_toRAM;
	wire [15:0] data_toRAM, data_fromRAM;
	
	TinyMIPS uut1 (clk, rst, data_fromRAM, wrEn, addr_toRAM, data_toRAM);

	blram #(SIZE, DEPTH) uut2 (clk, rst, wrEn, addr_toRAM, data_toRAM, data_fromRAM);

	initial begin
		clk = 1;
		forever
			#5 clk = ~clk;
	end

	initial begin
		rst = 1;
		repeat (10) @(posedge clk);
		rst <= #1 0;
		repeat (600) @(posedge clk);
		$finish;
	end
  
  	// I HAVE DONE THE WAVEFORMS SCREENSHOTS ONE BY ONE BUT TO SHOW IT WHEN CLICKED IN MY LINK I HAVE WRITTEN IT ALL TESTS IN ONE PAGE
	initial begin
		// Test 1: Sum of 1 to 5
      uut2.mem[0] = 16'b0111001000000001; // CPi R1 1 // i = 1
      uut2.mem[1] = 16'b0111010000000000; // CPi R2 0 // sum = 0
      uut2.mem[2] = 16'b0111011000000110; // CPi R3 6 // max = 6
      uut2.mem[3] = 16'b0000010010001000; // ADD R2 R2 R1 // sum = sum + i
      uut2.mem[4] = 16'b0001001001000001; // ADDi R1 R1 1 // i++
      uut2.mem[5] = 16'b1001001011111110; // BLT R1 R3 -2 // if (i < max) then go back to address 5-2=3
     end

  	initial begin
// Test 2: Sum of 5 numbers in the memory
// The result is stored at address 15
		uut2.mem[0] = 16'b0111001000000000;
		uut2.mem[1] = 16'b0111010000000000;
		uut2.mem[2] = 16'b0111011000000101;
        uut2.mem[3] = 16'b0100100001001010;
        uut2.mem[4] = 16'b0000010010100000;
		uut2.mem[5] = 16'b0001001001000001;
        uut2.mem[6] = 16'b1001001011111101;
        uut2.mem[7] = 16'b0101010001001010;
        //uut2.mem[8] = 16'b0111011000000110;
        //uut2.mem[9] = 16'b0000010010001000;
        uut2.mem[10] = 16'b0000000000000101;
        uut2.mem[11] = 16'b0000000000001000;
        uut2.mem[12] = 16'b0000000000001111;
        uut2.mem[13] = 16'b0000000000010001;
        uut2.mem[14] = 16'b0000000000010110;
        uut2.mem[15] = 16'b0000000000000000;
    end
 
  initial begin
      // Test 3: Factorial of 5
      	uut2.mem[0] = 16'b0111001000000001;
		uut2.mem[1] = 16'b0110010001000000;
		uut2.mem[2] = 16'b0111011000000110;
      	uut2.mem[3] = 16'b0010010010001000;
      	uut2.mem[4] = 16'b0001001001000001;
		uut2.mem[5] = 16'b1001001011111110;
    end
	initial begin
      // Test 4: In-place memory update
		uut2.mem[0] = 16'b0111001000000101;
		uut2.mem[1] = 16'b0111010000000000;
		uut2.mem[2] = 16'b0110011010000000;
      	uut2.mem[3] = 16'b0111100000000010;
      	uut2.mem[4] = 16'b0100101001001110;
		uut2.mem[5] = 16'b1000101011000100;
      	uut2.mem[6] = 16'b0001101101000101;
        uut2.mem[7] = 16'b0011101101100000;
        uut2.mem[8] = 16'b0101101001001110;
        uut2.mem[9] = 16'b0001001001111111;
        uut2.mem[10] = 16'b1010001010111010;
      	uut2.mem[15] = 16'b0000000000000101;
        uut2.mem[16] = 16'b0000000000000000;
        uut2.mem[17] = 16'b0000000000001111;
        uut2.mem[18] = 16'b0000000000010001;
        uut2.mem[19] = 16'b0000000000010110;
    end

  
	initial begin
    $dumpfile("dump.vcd"); $dumpvars;
    #1000 $finish;
  	end
  
endmodule

dump.vcd
$date
	Thu May 23 15:08:57 2024
$end

$version
	Synopsys VCS version U-2023.03-SP2_Full64
$end

$timescale
	1ps
$end

$comment Csum: 1 bd9349f13ab7045e $end


$scope module tb_TinyMIPS $end
$var reg 1 ! clk $end
$var reg 1 " rst $end
$var wire 1 # wrEn $end
$var wire 8 $ addr_toRAM [7:0] $end
$var wire 16 % data_toRAM [15:0] $end
$var wire 16 & data_fromRAM [15:0] $end

$scope module uut1 $end
$var wire 1 ! clk $end
$var wire 1 " rst $end
$var reg 1 # wrEn $end
$var wire 16 & data_fromRAM [15:0] $end
$var reg 16 % data_toRAM [15:0] $end
$var reg 8 $ addr_toRAM [7:0] $end
$var reg 3 ' st [2:0] $end
$var reg 3 ( stN [2:0] $end
$var reg 8 ) PC [7:0] $end
$var reg 8 * PCN [7:0] $end
$var reg 16 + IW [15:0] $end
$var reg 16 , IWN [15:0] $end
$var reg 16 - T1 [15:0] $end
$var reg 16 . T1N [15:0] $end
$var reg 16 / T2 [15:0] $end
$var reg 16 0 T2N [15:0] $end
$upscope $end


$scope module uut2 $end
$var wire 1 ! clk $end
$var wire 1 " rst $end
$var wire 1 # we $end
$var wire 8 $ addr [7:0] $end
$var wire 16 % din [15:0] $end
$var reg 16 & dout [15:0] $end
$upscope $end

$upscope $end

$enddefinitions $end

#0
$dumpvars
1!
1"
x#
bxxxxxxxxxxxxxxxx +
bxxxxxxxxxxxxxxxx ,
bxxxxxxxx )
b00000000 *
bxxxxxxxxxxxxxxxx -
bxxxxxxxxxxxxxxxx .
bxxxxxxxxxxxxxxxx /
bxxxxxxxxxxxxxxxx 0
bxxxxxxxxxxxxxxxx &
bxxx '
b000 (
bxxxxxxxx $
bxxxxxxxxxxxxxxxx %
$end
#5000
0!
#10000
1!
b000 '
b00000000 )
#15000
0!
#20000
1!
#25000
0!
#30000
1!
#35000
0!
#40000
1!
#45000
0!
#50000
1!
#55000
0!
#60000
1!
#65000
0!
#70000
1!
#75000
0!
#80000
1!
#85000
0!
#90000
1!
#95000
0!
#100000
1!
#101000
0"
b001 (
b00000000 $
0#
#105000
0!
#110000
1!
b001 '
b0111001000000101 &
b000 (
b00000001 *
bxxxxxxxx $
b0111001000000101 ,
#115000
0!
#120000
1!
b000 '
b00000001 )
b0111001000000101 +
bxxxxxxxxxxxxxxxx &
b001 (
b00000001 $
#125000
0!
#130000
1!
b001 '
b0111010000000000 &
b000 (
b00000010 *
bxxxxxxxx $
b0111010000000000 ,
#135000
0!
#140000
1!
b000 '
b00000010 )
b0111010000000000 +
bxxxxxxxxxxxxxxxx &
b001 (
b00000010 $
#145000
0!
#150000
1!
b001 '
b0110011010000000 &
b010 (
bxxxxxxxx $
b0110011010000000 ,
b0000000000000000 .
#155000
0!
#160000
1!
b010 '
b0110011010000000 +
b0000000000000000 -
bxxxxxxxxxxxxxxxx &
b000 (
b00000011 *
bxxxxxxxxxxxxxxxx .
#165000
0!
#170000
1!
b000 '
b00000011 )
bxxxxxxxxxxxxxxxx -
b001 (
b00000011 $
#175000
0!
#180000
1!
b001 '
b0111100000000010 &
b000 (
b00000100 *
bxxxxxxxx $
b0111100000000010 ,
#185000
0!
#190000
1!
b000 '
b00000100 )
b0111100000000010 +
bxxxxxxxxxxxxxxxx &
b001 (
b00000100 $
#195000
0!
#200000
1!
b001 '
b0100101001001110 &
b010 (
bxxxxxxxx $
b0100101001001110 ,
b0000000000000101 .
#205000
0!
#210000
1!
b010 '
b0100101001001110 +
b0000000000000101 -
bxxxxxxxxxxxxxxxx &
b011 (
b0000000000010011 0
#215000
0!
#220000
1!
b011 '
b0000000000010011 /
b000 (
b00000101 *
bxxxxxxxxxxxxxxxx 0
bxxxxxxxxxxxxxxxx .
b00010011 $
#225000
0!
#230000
1!
b000 '
b00000101 )
bxxxxxxxxxxxxxxxx -
bxxxxxxxxxxxxxxxx /
b0000000000010110 &
b001 (
b00000101 $
#235000
0!
#240000
1!
b001 '
b1000101011000100 &
b010 (
bxxxxxxxx $
b1000101011000100 ,
b000000000000000x .
#245000
0!
#250000
1!
b010 '
b1000101011000100 +
b000000000000000x -
bxxxxxxxxxxxxxxxx &
b011 (
b0000000000000000 0
#255000
0!
#260000
1!
b011 '
b0000000000000000 /
b000 (
b0000xxxx *
bxxxxxxxxxxxxxxxx 0
bxxxxxxxxxxxxxxxx .
#265000
0!
#270000
1!
b000 '
b0000xxxx )
bxxxxxxxxxxxxxxxx -
bxxxxxxxxxxxxxxxx /
b001 (
b0000xxxx $
#275000
0!
#280000
1!
b001 '
bxxx (
bxxxxxxxx $
bxxxxxxxxxxxxxxxx ,
#285000
0!
#290000
1!
bxxx '
bxxxxxxxxxxxxxxxx +
